<chess>
    <pieces>
        <pawn>
   __   
  /  \  
  \__/  
 /____\ 
  |  |  
  |__|  
 (====) 
 }===={ 
(______)
        </pawn>
        <rook>
 |'-'-'| 
 |_____| 
  |===|  
  |   |  
  |   |  
  )___(  
 (=====) 
 }====={ 
(_______)
        </rook>
        <knight>
  (\=,   
 //  .\  
(( \_  \ 
 ))  `\_)
(/     \ 
 | _.-'| 
  )___(  
 (=====) 
 }====={ 
(_______)
        </knight>
        <bishop>
    ()    
    /\    
   //\\   
  (    )  
   )__(   
  /____\  
   |  |   
   |  |   
  /____\  
 (======) 
 }======{ 
(________)
        </bishop>
        <queen>
    ()    
 .-:--:-. 
  \____/  
  {====}  
   )__(   
  /____\  
   |  |   
   |  |   
   |  |   
   |  |   
  /____\  
 (======) 
 }======{ 
(________)
        </queen>
        <king>
    _:_    
   '-.-'   
  __.'.__  
 |_______| 
  \=====/  
   )___(   
  /_____\  
   |   |   
   |   |   
   |   |   
   |   |   
   |   |   
  /_____\  
 (=======) 
 }======={ 
(_________)
        </king>
    </pieces>
    <colors>
        <square>
            <white>Gray</white>
            <black>DarkRed</black>
        </square>
        <piece>
            <white>White</white>
            <black>Black</black>
        </piece>
    </colors>
</chess>
